{"BaseModel.4d7be2a8-d794-4b67-8faf-63bd8da75ed5": {"__class__": "BaseModel", "id": "4d7be2a8-d794-4b67-8faf-63bd8da75ed5", "created_at": "2023-10-13T17:29:16.061961", "updated_at": "2023-10-13T17:29:16.061966"}, "User.8820ad00-6163-4ed8-a29d-508dea4692fd": {"__class__": "User", "id": "8820ad00-6163-4ed8-a29d-508dea4692fd", "created_at": "2023-10-13T17:29:16.061985", "updated_at": "2023-10-13T17:29:16.061990", "first_name": "Betty", "last_name": "Bar", "email": "airbnb@mail.com", "password": "root"}, "User.4a3f6338-7c2b-49f1-8b27-ad66536532c1": {"__class__": "User", "id": "4a3f6338-7c2b-49f1-8b27-ad66536532c1", "created_at": "2023-10-13T17:30:01.248511", "updated_at": "2023-10-13T17:30:01.248517", "first_name": "Betty", "last_name": "Bar", "email": "airbnb@mail.com", "password": "root"}, "User.031e16f2-7aee-462a-ace7-131881d8bf85": {"__class__": "User", "id": "031e16f2-7aee-462a-ace7-131881d8bf85", "created_at": "2023-10-13T17:44:31.593146", "updated_at": "2023-10-13T17:44:31.593153", "first_name": "Betty", "last_name": "Bar", "email": "airbnb@mail.com", "password": "root"}, "User.46a0afe6-5bc9-4379-b582-be6d00ed3613": {"__class__": "User", "id": "46a0afe6-5bc9-4379-b582-be6d00ed3613", "created_at": "2023-10-13T17:45:41.854456", "updated_at": "2023-10-13T17:45:41.854462", "first_name": "Betty", "last_name": "Bar", "email": "airbnb@mail.com", "password": "root"}, "User.8b979abd-fc0d-4953-b9f1-c39b5fdcab28": {"__class__": "User", "id": "8b979abd-fc0d-4953-b9f1-c39b5fdcab28", "created_at": "2023-10-13T17:46:29.577389", "updated_at": "2023-10-13T17:46:29.577395", "first_name": "Betty", "last_name": "Bar", "email": "airbnb@mail.com", "password": "root"}, "User.06e7e9c8-7827-45b9-a2fd-dc018f4cac4c": {"__class__": "User", "id": "06e7e9c8-7827-45b9-a2fd-dc018f4cac4c", "created_at": "2023-10-13T17:47:09.138163", "updated_at": "2023-10-13T17:47:09.138172", "first_name": "Betty", "last_name": "Bar", "email": "airbnb@mail.com", "password": "root"}, "User.1ba1ba36-753c-4d67-a3d2-23f2e2751a36": {"__class__": "User", "id": "1ba1ba36-753c-4d67-a3d2-23f2e2751a36", "created_at": "2023-10-13T17:47:10.976575", "updated_at": "2023-10-13T17:47:10.976584", "first_name": "Betty", "last_name": "Bar", "email": "airbnb@mail.com", "password": "root"}, "User.7e83bc66-cd0c-40ce-8abb-3b65e64f45e3": {"__class__": "User", "id": "7e83bc66-cd0c-40ce-8abb-3b65e64f45e3", "created_at": "2023-10-13T17:47:29.197754", "updated_at": "2023-10-13T17:47:29.197763", "first_name": "Betty", "last_name": "Bar", "email": "airbnb@mail.com", "password": "root"}, "User.b45a0dd3-f742-49a8-b045-90ecd2a20f62": {"__class__": "User", "id": "b45a0dd3-f742-49a8-b045-90ecd2a20f62", "created_at": "2023-10-13T17:47:36.175590", "updated_at": "2023-10-13T17:47:36.175613", "first_name": "Betty", "last_name": "Bar", "email": "airbnb@mail.com", "password": "root"}, "User.aedf66f1-a229-4286-8835-50d0a70d7841": {"__class__": "User", "id": "aedf66f1-a229-4286-8835-50d0a70d7841", "created_at": "2023-10-13T17:48:24.027784", "updated_at": "2023-10-13T17:48:24.027797", "first_name": "Betty", "last_name": "Bar", "email": "airbnb@mail.com", "password": "root"}, "User.84a093f5-6c4f-4d1c-bcee-a164d202a743": {"__class__": "User", "id": "84a093f5-6c4f-4d1c-bcee-a164d202a743", "created_at": "2023-10-13T17:50:49.792450", "updated_at": "2023-10-13T17:50:49.792459", "first_name": "Betty", "last_name": "Bar", "email": "airbnb@mail.com", "password": "root"}, "BaseModel.f6f0d434-9f03-4e77-bb3e-690c4aeec1da": {"__class__": "BaseModel", "name": "My_First_Model", "my_number": 89, "id": "f6f0d434-9f03-4e77-bb3e-690c4aeec1da", "created_at": "2023-10-13T18:04:24.315188", "updated_at": "2023-10-13T18:04:24.315194"}, "BaseModel.fefe98a9-fa73-4f6c-b7b8-f19568dca4cd": {"__class__": "BaseModel", "name": "My_First_Model", "my_number": 89, "id": "fefe98a9-fa73-4f6c-b7b8-f19568dca4cd", "created_at": "2023-10-13T18:05:07.743240", "updated_at": "2023-10-13T18:05:07.743249"}, "BaseModel.70c58be5-387a-4c3f-9cd3-a055b9594559": {"__class__": "BaseModel", "name": "My_First_Model", "my_number": 89, "id": "70c58be5-387a-4c3f-9cd3-a055b9594559", "created_at": "2023-10-13T18:06:14.259025", "updated_at": "2023-10-13T18:06:14.259033"}, "BaseModel.fc7169cc-0c0c-48c2-ad97-fc3d8586aff8": {"__class__": "BaseModel", "name": "My_First_Model", "my_number": 89, "id": "fc7169cc-0c0c-48c2-ad97-fc3d8586aff8", "created_at": "2023-10-13T18:06:17.317976", "updated_at": "2023-10-13T18:06:17.317982"}, "BaseModel.644a8993-95de-46d5-9b4d-7418b595f8aa": {"__class__": "BaseModel", "id": "644a8993-95de-46d5-9b4d-7418b595f8aa", "created_at": "2023-10-13T18:07:23.030126", "updated_at": "2023-10-13T18:07:23.030132", "name": "My_First_Model", "my_number": 89}}